stopots_bot/__init__.py
stopots_bot/bot.py
stopots_bot/command_line.py
stopots_bot/constants.py
stopots_bot/dictionary.json
stopots_bot/dictionary.py
stopots_bot/menu.py
stopots_bot/start.py
stopots_bot/utils.py
stopots_bot/webdriver.py
stopots_bot-1.2.0.dist-info/LICENSE
stopots_bot-1.2.0.dist-info/METADATA
stopots_bot-1.2.0.dist-info/WHEEL
stopots_bot-1.2.0.dist-info/entry_points.txt
stopots_bot-1.2.0.dist-info/top_level.txt
stopots_bot-1.2.0.dist-info/RECORD
