Metadata-Version: 2.1
Name: stopots-bot
Version: 1.2.0
Summary: auto play stopots
Home-page: https://github.com/Lucas8x/stopots-bot
Author: Lucas8x
Author-email: 
License: MIT
Platform: UNKNOWN
Classifier: Programming Language :: Python :: 3
Classifier: Environment :: Console
Classifier: Intended Audience :: End Users/Desktop
Classifier: License :: OSI Approved :: MIT License
Classifier: Natural Language :: Portuguese (Brazilian)
Requires-Python: >=3.9
Requires-Dist: selenium (==3.141.0)
Requires-Dist: webdriver-manager (==3.2.2)
Requires-Dist: tabulate (==0.8.7)
